MANIFEST.in
README.md
setup.py
ELF2deb.egg-info/PKG-INFO
ELF2deb.egg-info/SOURCES.txt
ELF2deb.egg-info/dependency_links.txt
ELF2deb.egg-info/entry_points.txt
ELF2deb.egg-info/requires.txt
ELF2deb.egg-info/top_level.txt
elf2deb/__init__.py
elf2deb/__main__.py
elf2deb/elf2deb.pyz
elf2deb/templates/Makefile
elf2deb/templates/debian/compat
elf2deb/templates/debian/control
elf2deb/templates/debian/rules
elf2deb/templates/debian/source/format