Metadata-Version: 2.1
Name: ELF2deb
Version: 1.2.0
Summary: Convert any single (or multiple) executable file(s) to .deb package
Home-page: https://github.com/NicolaiSoeborg/ELF2deb/
Author: Nicolai Søborg
Author-email: elf2deb@xn--sb-lka.org
License: MIT
Platform: UNKNOWN
Classifier: Intended Audience :: Developers
Classifier: Intended Audience :: System Administrators
Classifier: License :: OSI Approved :: MIT License
Classifier: Programming Language :: Python :: 3
Classifier: Programming Language :: Python :: 3.5
Classifier: Programming Language :: Python :: 3.6
Classifier: Programming Language :: Python :: 3.7
Classifier: Topic :: Software Development :: Build Tools
Classifier: Topic :: System :: Archiving :: Packaging
Classifier: Topic :: System :: Installation/Setup
